choosy/__about__.py
choosy/__init__.py
choosy/base.py
choosy-0.0.5.dist-info/METADATA
choosy-0.0.5.dist-info/WHEEL
choosy-0.0.5.dist-info/licenses/LICENSE
choosy-0.0.5.dist-info/RECORD
