Metadata-Version: 2.1
Name: choosy
Version: 0.0.5
Project-URL: Documentation, https://github.com/ceesem/choosy#readme
Project-URL: Issues, https://github.com/ceesem/choosy/issues
Project-URL: Source, https://github.com/ceesem/choosy
Author-email: Casey Schneider-Mizell <caseysm@gmail.com>
License-Expression: BSD-3-Clause
License-File: LICENSE
Classifier: Development Status :: 4 - Beta
Classifier: Programming Language :: Python
Classifier: Programming Language :: Python :: 3.7
Classifier: Programming Language :: Python :: 3.8
Classifier: Programming Language :: Python :: 3.9
Classifier: Programming Language :: Python :: 3.10
Classifier: Programming Language :: Python :: 3.11
Classifier: Programming Language :: Python :: Implementation :: CPython
Classifier: Programming Language :: Python :: Implementation :: PyPy
Requires-Python: >=3.7
Requires-Dist: numpy
Requires-Dist: pandas
